<?xml version="1.0" encoding="UTF-8"?>
<?xml-model href="comments_schema.rnc" type="application/relax-ng-compact-syntax"?>
<media source="youtube" category="music ameteur cover">
    
    <title>Hold On To Me - Mayday Parade (Bethan Mary Leadley Cover)</title>
    
    <mainContent>
        <link>https://www.youtube.com/watch?v=SiPGt8P0GLI</link>
        <author>acousitcbethan</author>
        <description>
            
            Published on Jan 29, 2014
            
            Make sure you get check out their album on itunes (is well creepy sick) https://itunes.apple.com/us/album/mon...
            
            Artist
            Mayday Parade
            Category
            Music
            License
            Standard YouTube License
            
        </description>
        <statistics>
            <subscribers>28213</subscribers>
            <views>11165</views>
            <likes>534</likes>
            <dislikes>15</dislikes>
            <totalComments>59</totalComments>
            <publishDate>01/29/2014</publishDate>
        </statistics>
    </mainContent>
    
    <commentSection>
        <comment tone="positive">
            <commenter>doddleoddle</commenter>
            <sentence structure="poor">Befon <emote>&lt;3</emote> you get better every day <emote>&lt;3</emote></sentence>
        </comment>
        <comment tone="neutral">
            <commenter>Jessica Francesca</commenter>
            <sentence structure="good">Was there a tutorial video or something you found to learn this? <acronym>Bc</acronym> I can't find any</sentence>
        </comment>
        <comment tone="positive">
            <commenter>Josi Campos</commenter>
            <sentence structure="good">I love all of your acoustic covers and songs! Your voice fits well with acoustic music<expunc>!!</expunc> <emote>:)</emote> Truly beautiful.</sentence>
        </comment>
        <comment tone="neutral">
            <commenter>acousticbethan</commenter>  
            <sentence structure="good">Check out my new cover of @Mayday_Parade's Hold On To Me on my cover channel!</sentence>
        </comment>
        <comment tone="positive">
             <commenter>Paulina T</commenter>
            <sentence structure="good">this is your best cover ever! You sang it really beautifully and this type of music really brings out the best in your voice. I love it.</sentence>
        </comment>
        <comment tone="positive">
            <commenter>Geovane Moraisx</commenter>
            <sentence structure="good">Love it.</sentence>
        </comment>
        <comment tone="neutral">
            <commenter>Mariana Nenadovic</commenter>
            <sentence structure="good">Can you please do a tutorial for this<expunc>??</expunc> or make a tab<expunc>??</expunc></sentence></comment>
            <comment tone="positive">
                <commenter>WayOutThere</commenter>
                <sentence structure="good">I saw them at Warped a couple days ago and got to wish Derek a happy birthday. Your voice was absolutely amazing for this song and acoustic covers. stay wonderful and beautiful &lt;3</sentence>
            </comment>
            <comment tone="neutral">
                <commenter>KaiiTheBaii</commenter>
                <sentence structure="good">What's funny is we were at the same concert but I didn't get to stop you and say hi <emote>:/</emote></sentence>
            </comment>
            <comment tone="positive">
                <commenter>Lucy Bennefeld</commenter>
               <sentence structure="good">You're an amazing singer and you're really pretty.</sentence>
            </comment>
    </commentSection>
    
</media>
