<?xml version="1.0" encoding="UTF-8"?>
<?xml-model href="../../schemas/LocationSchema.rnc" type="application/relax-ng-compact-syntax"?><location type="city/town">
    <name n="Fuchsia City">Fuchsia City</name>
    <des>A historic village that has become new.</des>
    <PoI>

        <place>
            <placeName>Safari Zone</placeName>
            <des>The <pref>Safari Zone</pref> is a special Pokémon preserve where Trainers can enter
                to capture certain types of Pokémon. It is owned by the <pers>Warden</pers>. For
                    <item>PokémonDollar</item> 500, the <pers>player</pers> will receive 30
                    <item>Safari Balls</item>. With a large area to cover, Trainers
                must plan out their destination so as to arrive in time to capture all the Pokémon
                they want. </des>
        </place>

        <place>
            <placeName>Pokemon Zoo</placeName>
            <des>There are Pokémon on display, including <pokemon dexNum="113">Chansey</pokemon>,
                    <pokemon dexNum="131">Lapras</pokemon>, <pokemon dexNum="100">Voltorb</pokemon>,
                    <pokemon dexNum="115">Kangaskhan</pokemon>, and <pokemon dexNum="079">Slowpoke</pokemon>. In addition, the <item>Fossil</item> that the
                    <pers>player</pers> "shares" with the <pers>Super Nerd</pers> in Mt. Moon
                appears here as well. It will be a <pokemon dexNum="140">Kabuto</pokemon> if the
                player chose the <item>Helix Fossil</item>, and an <pokemon dexNum="138">Omanyte</pokemon> if the <pers>player</pers> chose the <item>Dome
                Fossil</item>.</des>
        </place>

        <place>
            <placeName>Fuchsia Gym</placeName>
            <des>The <pref>Fuchsia Gym</pref> is the official Gym of <pref>Fuchsia City</pref>. It is based on Poison-type
                Pokémon. The Gym Leader is <pers>Koga</pers>.</des>
        </place>

    </PoI>
</location>