<?xml version="1.0" encoding="UTF-8"?>
<location type="route">
    <route num="25">Route 25</route>
    <des>Heading from west to east, <pref>Route 25</pref> initially begins as an extension to
            <pref>Route 24</pref>. To the east, <pref>Route 25</pref> comes to a maze of trees or
        shrubs. </des>
    <encounters>
        <pokemon dexNum="010">Caterpie</pokemon>
        <pokemon dexNum="011">Metapod</pokemon>
        <pokemon dexNum="013">Weedle</pokemon>
        <pokemon dexNum="014">Kakuna</pokemon>
        <pokemon dexNum="016">Pidgey</pokemon>
        <pokemon dexNum="043">Oddish</pokemon>
        <pokemon dexNum="063">Abra</pokemon>
        <pokemon dexNum="069">Bellsprout</pokemon>
        <pokemon dexNum="129">Magikarp</pokemon>
        <pokemon dexNum="060">Poliwag</pokemon>
        <pokemon dexNum="118">Goldeen</pokemon>
        <pokemon dexNum="054">Psyduck</pokemon>
        <pokemon dexNum="098">Krabby</pokemon>
    </encounters>
</location>