<?xml version="1.0" encoding="UTF-8"?>
<xqdoc:xqdoc xmlns:xqdoc="http://www.xqdoc.org/1.0"><xqdoc:control><xqdoc:date>2015-05-06T12:07:02.066-04:00</xqdoc:date><xqdoc:location>/db/apps/dashboard/plugins/userManager/jsjson.xqm</xqdoc:location></xqdoc:control><xqdoc:module type="library"><xqdoc:uri>http://johnsnelson/json</xqdoc:uri><xqdoc:name>jsjson</xqdoc:name><xqdoc:comment><xqdoc:description/></xqdoc:comment></xqdoc:module><xqdoc:functions><xqdoc:function><xqdoc:name>jsjson:decode-hex-string</xqdoc:name><xqdoc:signature>jsjson:decode-hex-string($val as xs:string) as xs:integer</xqdoc:signature><xqdoc:comment><xqdoc:description/><xqdoc:param>$val </xqdoc:param><xqdoc:return>xs:integer</xqdoc:return></xqdoc:comment></xqdoc:function><xqdoc:function><xqdoc:name>jsjson:escape-json-string</xqdoc:name><xqdoc:signature>jsjson:escape-json-string($val as xs:string) as xs:string</xqdoc:signature><xqdoc:comment><xqdoc:description/><xqdoc:param>$val </xqdoc:param><xqdoc:return>xs:string</xqdoc:return></xqdoc:comment></xqdoc:function><xqdoc:function><xqdoc:name>jsjson:parse-json</xqdoc:name><xqdoc:signature>jsjson:parse-json($json as xs:string) as element()?</xqdoc:signature><xqdoc:comment><xqdoc:description/><xqdoc:param>$json </xqdoc:param><xqdoc:return>element()?</xqdoc:return></xqdoc:comment></xqdoc:function><xqdoc:function><xqdoc:name>jsjson:serialize-json</xqdoc:name><xqdoc:signature>jsjson:serialize-json($json-xml as element()?) as xs:string?</xqdoc:signature><xqdoc:comment><xqdoc:description/><xqdoc:param>$json-xml? </xqdoc:param><xqdoc:return>xs:string?</xqdoc:return></xqdoc:comment></xqdoc:function><xqdoc:function><xqdoc:name>jsjson:unescape-json-string</xqdoc:name><xqdoc:signature>jsjson:unescape-json-string($val as xs:string) as xs:string</xqdoc:signature><xqdoc:comment><xqdoc:description/><xqdoc:param>$val </xqdoc:param><xqdoc:return>xs:string</xqdoc:return></xqdoc:comment></xqdoc:function></xqdoc:functions></xqdoc:xqdoc>