<collection xmlns="http://exist.sourceforge.net/NS/exist" name="/db/Erica_queries" version="1" owner="ezimmer" group="ezimmer" mode="755" created="2015-09-12T13:39:03.229-04:00">
    <acl entries="0" version="1"/>
    <resource type="BinaryResource" name="myapp8" skip="no" owner="ezimmer" group="ezimmer" mode="755" created="2017-07-27T20:10:08.531-04:00" modified="2017-07-27T20:10:20.444-04:00" filename="myapp8" mimetype="application/xquery">
        <acl entries="0" version="1"/>
    </resource>
    <resource type="BinaryResource" name="myapp10" skip="no" owner="ezimmer" group="ezimmer" mode="755" created="2017-07-27T20:14:17.086-04:00" modified="2017-07-27T20:14:17.086-04:00" filename="myapp10" mimetype="application/xquery">
        <acl entries="0" version="1"/>
    </resource>
    <resource type="BinaryResource" name="myapp11" skip="no" owner="ezimmer" group="ezimmer" mode="755" created="2017-07-27T20:16:02.956-04:00" modified="2017-07-27T20:16:02.956-04:00" filename="myapp11" mimetype="application/xquery">
        <acl entries="0" version="1"/>
    </resource>
    <resource type="BinaryResource" name="myapp9" skip="no" owner="ezimmer" group="ezimmer" mode="755" created="2017-07-27T20:11:32.895-04:00" modified="2017-07-27T20:17:11.66-04:00" filename="myapp9" mimetype="application/xquery">
        <acl entries="0" version="1"/>
    </resource>
    <resource type="BinaryResource" name="myapp12-partial" skip="no" owner="ezimmer" group="ezimmer" mode="755" created="2017-07-27T20:22:42.309-04:00" modified="2017-07-27T20:44:18.075-04:00" filename="myapp12-partial" mimetype="application/xquery">
        <acl entries="0" version="1"/>
    </resource>
    <resource type="BinaryResource" name="elisa-mod-MissJames" skip="no" owner="admin" group="alex" mode="755" created="2015-09-15T13:24:15.205-04:00" modified="2015-09-19T12:24:13.529-04:00" filename="elisa-mod-MissJames" mimetype="application/xquery">
        <acl entries="0" version="1"/>
    </resource>
    <resource type="BinaryResource" name="elisa-frequency-XMLout" skip="no" owner="admin" group="alex" mode="755" created="2015-09-19T12:26:06.283-04:00" modified="2015-09-19T12:26:06.283-04:00" filename="elisa-frequency-XMLout" mimetype="application/xquery">
        <acl entries="0" version="1"/>
    </resource>
    <resource type="BinaryResource" name="draft_mez_hello_world" skip="no" owner="ezimmer" group="ezimmer" mode="755" created="2015-09-12T13:47:30.095-04:00" modified="2015-09-12T13:48:17.322-04:00" filename="draft_mez_hello_world" mimetype="application/xquery">
        <acl entries="0" version="1"/>
    </resource>
    <resource type="BinaryResource" name="draft_mez_count_Miss_James_instances" skip="no" owner="ezimmer" group="ezimmer" mode="755" created="2015-09-12T17:31:01.117-04:00" modified="2015-11-13T08:44:43.804-05:00" filename="draft_mez_count_Miss_James_instances" mimetype="application/xquery">
        <acl entries="0" version="1"/>
    </resource>
    <resource type="BinaryResource" name="draft_mez_count_distinct_vals_all_persName" skip="no" owner="ezimmer" group="ezimmer" mode="755" created="2015-09-12T14:04:51.87-04:00" modified="2015-11-13T08:44:47.679-05:00" filename="draft_mez_count_distinct_vals_all_persName" mimetype="application/xquery">
        <acl entries="0" version="1"/>
    </resource>
    <resource type="BinaryResource" name="erica_modifying_counts_of_xml" skip="no" owner="ezimmer" group="ezimmer" mode="755" created="2015-09-19T12:28:04.578-04:00" modified="2015-09-19T14:24:30.498-04:00" filename="erica_modifying_counts_of_xml" mimetype="application/xquery">
        <acl entries="0" version="1"/>
    </resource>
    <resource type="BinaryResource" name="myapp13" skip="no" owner="ezimmer" group="ezimmer" mode="755" created="2017-07-27T20:59:31.664-04:00" modified="2017-07-27T21:06:29.097-04:00" filename="myapp13" mimetype="application/xquery">
        <acl entries="0" version="1"/>
    </resource>
    <resource type="BinaryResource" name="mysecondapp" skip="no" owner="ezimmer" group="ezimmer" mode="755" created="2017-07-27T19:45:33.444-04:00" modified="2017-07-27T19:45:33.444-04:00" filename="mysecondapp" mimetype="application/xquery">
        <acl entries="0" version="1"/>
    </resource>
    <resource type="BinaryResource" name="myapp15" skip="no" owner="ezimmer" group="ezimmer" mode="755" created="2017-07-27T21:07:56.593-04:00" modified="2017-07-27T21:08:07.582-04:00" filename="myapp15" mimetype="application/xquery">
        <acl entries="0" version="1"/>
    </resource>
    <resource type="BinaryResource" name="tester-elisa" skip="no" owner="admin" group="alex" mode="755" created="2015-09-20T11:25:26.701-04:00" modified="2015-09-20T11:25:26.701-04:00" filename="tester-elisa" mimetype="application/xquery">
        <acl entries="0" version="1"/>
    </resource>
    <resource type="BinaryResource" name="draft_mez_list_distinct_persNames_12-9-15" skip="no" owner="ezimmer" group="ezimmer" mode="755" created="2015-09-12T17:05:22.44-04:00" modified="2015-09-12T17:24:10.421-04:00" filename="draft_mez_list_distinct_persNames_12-9-15" mimetype="application/xquery">
        <acl entries="0" version="1"/>
    </resource>
    <resource type="BinaryResource" name="draft_mez_count_letters_query" skip="no" owner="ezimmer" group="ezimmer" mode="755" created="2015-09-14T08:45:02.421-04:00" modified="2015-09-14T08:46:12.311-04:00" filename="draft_mez_count_letters_query" mimetype="application/xquery">
        <acl entries="0" version="1"/>
    </resource>
    <resource type="BinaryResource" name="draft_mez_count_number_paras" skip="no" owner="ezimmer" group="ezimmer" mode="755" created="2015-09-14T10:27:32.782-04:00" modified="2015-09-14T10:27:32.782-04:00" filename="draft_mez_count_number_paras" mimetype="application/xquery">
        <acl entries="0" version="1"/>
    </resource>
    <resource type="BinaryResource" name="draft_mez_return_all_persNames" skip="no" owner="ezimmer" group="ezimmer" mode="755" created="2015-09-14T11:53:59.646-04:00" modified="2015-09-14T11:53:59.646-04:00" filename="draft_mez_return_all_persNames" mimetype="application/xquery">
        <acl entries="0" version="1"/>
    </resource>
    <resource type="BinaryResource" name="draft_mez_count_persNames_opening_and_body" skip="no" owner="ezimmer" group="ezimmer" mode="755" created="2015-09-15T10:25:57.471-04:00" modified="2015-09-15T10:25:57.471-04:00" filename="draft_mez_count_persNames_opening_and_body" mimetype="application/xquery">
        <acl entries="0" version="1"/>
    </resource>
    <resource type="BinaryResource" name="draft_mez_count_number_persName" skip="no" owner="ezimmer" group="ezimmer" mode="755" created="2015-09-14T10:29:05.739-04:00" modified="2015-09-15T13:15:19.69-04:00" filename="draft_mez_count_number_persName" mimetype="application/xquery">
        <acl entries="0" version="1"/>
    </resource>
    <resource type="BinaryResource" name="draft_mez_retrieve_1_doc" skip="no" owner="ezimmer" group="ezimmer" mode="755" created="2015-09-12T13:51:48.106-04:00" modified="2015-09-12T13:56:55.006-04:00" filename="draft_mez_retrieve_1_doc" mimetype="application/xquery">
        <acl entries="0" version="1"/>
    </resource>
    <resource type="BinaryResource" name="elisa-pipeUnifierSample" skip="no" owner="admin" group="alex" mode="755" created="2015-09-19T12:52:06.835-04:00" modified="2015-09-19T12:52:06.835-04:00" filename="elisa-pipeUnifierSample" mimetype="application/xquery">
        <acl entries="0" version="1"/>
    </resource>
    <resource type="BinaryResource" name="Mitford-CoCit-Tables" skip="no" owner="admin" group="alex" mode="755" created="2015-09-19T14:29:37.506-04:00" modified="2015-09-19T16:04:10.366-04:00" filename="Mitford-CoCit-Tables" mimetype="application/xquery">
        <acl entries="0" version="1"/>
    </resource>
    <resource type="BinaryResource" name="myapp14-json" skip="no" owner="ezimmer" group="ezimmer" mode="755" created="2017-07-27T21:06:03.35-04:00" modified="2017-07-27T21:06:22.217-04:00" filename="myapp14-json" mimetype="application/xquery">
        <acl entries="0" version="1"/>
    </resource>
    <resource type="BinaryResource" name="Mitford_passages_only" skip="no" owner="ezimmer" group="ezimmer" mode="755" created="2015-10-19T13:43:15.377-04:00" modified="2015-10-19T13:43:15.377-04:00" filename="Mitford_passages_only" mimetype="application/xquery">
        <acl entries="0" version="1"/>
    </resource>
    <resource type="BinaryResource" name="draft_mez_coll_titleStmt_title_2" skip="no" owner="ezimmer" group="ezimmer" mode="755" created="2015-09-12T13:43:14.777-04:00" modified="2015-09-12T13:59:38.255-04:00" filename="draft_mez_coll_titleStmt_title_2" mimetype="application/xquery">
        <acl entries="0" version="1"/>
    </resource>
    <resource type="BinaryResource" name="myapp4-text" skip="no" owner="ezimmer" group="ezimmer" mode="755" created="2017-07-27T19:54:09.916-04:00" modified="2017-07-27T19:54:09.916-04:00" filename="myapp4-text" mimetype="application/xquery">
        <acl entries="0" version="1"/>
    </resource>
    <resource type="BinaryResource" name="my-first-app" skip="no" owner="ezimmer" group="ezimmer" mode="644" created="2017-07-27T19:37:55.514-04:00" modified="2017-07-27T19:40:49.892-04:00" filename="my-first-app" mimetype="application/xquery">
        <acl entries="0" version="1"/>
    </resource>
    <resource type="BinaryResource" name="myapp5" skip="no" owner="ezimmer" group="ezimmer" mode="755" created="2017-07-27T19:55:23.33-04:00" modified="2017-07-27T20:01:30.265-04:00" filename="myapp5" mimetype="application/xquery">
        <acl entries="0" version="1"/>
    </resource>
    <resource type="BinaryResource" name="myapp6" skip="no" owner="ezimmer" group="ezimmer" mode="755" created="2017-07-27T20:05:45.546-04:00" modified="2017-07-27T20:05:45.546-04:00" filename="myapp6" mimetype="application/xquery">
        <acl entries="0" version="1"/>
    </resource>
    <resource type="BinaryResource" name="myapp7" skip="no" owner="ezimmer" group="ezimmer" mode="755" created="2017-07-27T20:09:34.09-04:00" modified="2017-07-27T20:09:34.09-04:00" filename="myapp7" mimetype="application/xquery">
        <acl entries="0" version="1"/>
    </resource>
    <subcollection name="queries1" filename="queries1"/>
</collection>