<collection xmlns="http://exist.sourceforge.net/NS/exist" name="/db/brandnew/Albums(updated)/TheDevilAndGodAreRagingInsideMe" version="1" owner="bec80" group="dh-group" mode="755" created="2020-04-23T20:35:32.489Z">
    <acl entries="0" version="1"/>
    <resource type="XMLResource" name="degausser.xml" skip="no" owner="bec80" group="dh-group" mode="644" created="2020-04-23T20:35:32.489Z" modified="2020-04-23T20:35:32.489Z" filename="degausser.xml" mimetype="application/xml">
        <acl entries="0" version="1"/>
    </resource>
    <resource type="XMLResource" name="jesus-christ.xml" skip="no" owner="bec80" group="dh-group" mode="644" created="2020-04-23T20:35:32.564Z" modified="2020-04-23T20:35:32.564Z" filename="jesus-christ.xml" mimetype="application/xml">
        <acl entries="0" version="1"/>
    </resource>
    <resource type="XMLResource" name="the-archers-bows-have-broken.xml" skip="no" owner="bec80" group="dh-group" mode="644" created="2020-04-23T20:35:32.619Z" modified="2020-04-23T20:35:32.619Z" filename="the-archers-bows-have-broken.xml" mimetype="application/xml">
        <acl entries="0" version="1"/>
    </resource>
    <resource type="XMLResource" name="millstone.xml" skip="no" owner="bec80" group="dh-group" mode="644" created="2020-04-23T20:35:32.688Z" modified="2020-04-23T20:35:32.688Z" filename="millstone.xml" mimetype="application/xml">
        <acl entries="0" version="1"/>
    </resource>
    <resource type="XMLResource" name="limousine.xml" skip="no" owner="bec80" group="dh-group" mode="644" created="2020-04-23T20:35:32.745Z" modified="2020-04-23T20:35:32.745Z" filename="limousine.xml" mimetype="application/xml">
        <acl entries="0" version="1"/>
    </resource>
    <resource type="XMLResource" name="luca.xml" skip="no" owner="bec80" group="dh-group" mode="644" created="2020-04-23T20:35:32.804Z" modified="2020-04-23T20:35:32.804Z" filename="luca.xml" mimetype="application/xml">
        <acl entries="0" version="1"/>
    </resource>
    <resource type="XMLResource" name="welcome-to-bangkok.xml" skip="no" owner="bec80" group="dh-group" mode="644" created="2020-04-23T20:35:32.86Z" modified="2020-04-23T20:35:32.86Z" filename="welcome-to-bangkok.xml" mimetype="application/xml">
        <acl entries="0" version="1"/>
    </resource>
    <resource type="XMLResource" name="you-wont-know.xml" skip="no" owner="bec80" group="dh-group" mode="644" created="2020-04-23T20:35:32.915Z" modified="2020-04-23T20:35:32.915Z" filename="you-wont-know.xml" mimetype="application/xml">
        <acl entries="0" version="1"/>
    </resource>
    <resource type="XMLResource" name="untitled.xml" skip="no" owner="bec80" group="dh-group" mode="644" created="2020-04-23T20:35:32.965Z" modified="2020-04-23T20:35:32.965Z" filename="untitled.xml" mimetype="application/xml">
        <acl entries="0" version="1"/>
    </resource>
    <resource type="XMLResource" name="not-the-sun.xml" skip="no" owner="bec80" group="dh-group" mode="644" created="2020-04-23T20:35:33.018Z" modified="2020-04-23T20:35:33.018Z" filename="not-the-sun.xml" mimetype="application/xml">
        <acl entries="0" version="1"/>
    </resource>
    <resource type="XMLResource" name="sowing-season-yeah.xml" skip="no" owner="bec80" group="dh-group" mode="644" created="2020-04-23T20:35:33.073Z" modified="2020-04-23T20:35:33.073Z" filename="sowing-season-yeah.xml" mimetype="application/xml">
        <acl entries="0" version="1"/>
    </resource>
    <resource type="XMLResource" name="handcuffs.xml" skip="no" owner="bec80" group="dh-group" mode="644" created="2020-04-23T20:35:33.122Z" modified="2020-04-23T20:35:33.122Z" filename="handcuffs.xml" mimetype="application/xml">
        <acl entries="0" version="1"/>
    </resource>
</collection>