<?xml version="1.0" encoding="UTF-8"?>
<?xml-model href="../../schemas/LocationSchema.rnc" type="application/relax-ng-compact-syntax"?><location type="route">
    <route num="12">route 12</route>
    <des>A bridge known for its fishing where fishermen gather. It's also called "<pref>Silence
            Bridge</pref>." The <pref>Silence Bridge</pref> makes up most of <pref>Route 12</pref>.
        The first intersection on the <pref>Silence Bridge</pref> portion of <pref>Route 12</pref>
        is yet another of the three-way variety.</des>
    <encounters>
        <pokemon dexNum="016">Pidgey</pokemon>
        <pokemon dexNum="043">Oddish</pokemon>
        <pokemon dexNum="044">Gloom</pokemon>
        <pokemon dexNum="048">Venonat</pokemon>
        <pokemon dexNum="069">Bellsprout</pokemon>
        <pokemon dexNum="070">Weepinbell</pokemon>
        <pokemon dexNum="129">Magikarp</pokemon>
        <pokemon dexNum="060">Poliwag</pokemon>
        <pokemon dexNum="118">Goldeen</pokemon>
        <pokemon dexNum="098">Krabby</pokemon>
        <pokemon dexNum="072">Tentacool</pokemon>
    </encounters>
</location>