<collection xmlns="http://exist.sourceforge.net/NS/exist" name="/db/oHaraQueries" version="1" owner="ldm37" group="ldm37" mode="755" created="2014-12-01T12:19:42.948-05:00">
    <acl entries="0" version="1"/>
    <resource type="BinaryResource" name="foreignLanguageQuery" skip="no" owner="ldm37" group="ldm37" mode="755" created="2014-12-05T06:44:52.144-05:00" modified="2014-12-17T00:40:41.849-05:00" filename="foreignLanguageQuery" mimetype="application/xquery">
        <acl entries="0" version="1"/>
    </resource>
    <resource type="BinaryResource" name="lineCountQuery" skip="no" owner="ldm37" group="ldm37" mode="755" created="2014-12-01T12:19:58.026-05:00" modified="2014-12-01T12:52:23.649-05:00" filename="lineCountQuery" mimetype="application/xquery">
        <acl entries="0" version="1"/>
    </resource>
    <resource type="BinaryResource" name="referenceQuery" skip="no" owner="ldm37" group="ldm37" mode="755" created="2014-12-04T22:51:11.397-05:00" modified="2014-12-04T22:51:11.397-05:00" filename="referenceQuery" mimetype="application/xquery">
        <acl entries="0" version="1"/>
    </resource>
    <resource type="BinaryResource" name="indivReferenceQuery" skip="no" owner="ebb8" group="ebb8" mode="755" created="2014-12-10T13:32:44.756-05:00" modified="2014-12-10T13:38:13.914-05:00" filename="indivReferenceQuery" mimetype="application/xquery">
        <acl entries="0" version="1"/>
    </resource>
    <resource type="BinaryResource" name="refCountQuery" skip="no" owner="ldm37" group="ldm37" mode="755" created="2014-12-05T01:41:57.156-05:00" modified="2014-12-17T00:37:35.628-05:00" filename="refCountQuery" mimetype="application/xquery">
        <acl entries="0" version="1"/>
    </resource>
    <resource type="BinaryResource" name="peopleCountQuery" skip="no" owner="ldm37" group="ldm37" mode="755" created="2014-12-05T06:07:07.786-05:00" modified="2014-12-17T00:39:04.895-05:00" filename="peopleCountQuery" mimetype="application/xquery">
        <acl entries="0" version="1"/>
    </resource>
</collection>